jetshift_core/__init__.py
jetshift_core/commands/__init__.py
jetshift_core/commands/banners.py
jetshift_core/commands/dev.py
jetshift_core/commands/job.py
jetshift_core/commands/listener.py
jetshift_core/commands/main.py
jetshift_core/commands/make.py
jetshift_core/commands/migrations/__init__.py
jetshift_core/commands/migrations/clickhouse.py
jetshift_core/commands/migrations/common.py
jetshift_core/commands/migrations/migration.py
jetshift_core/commands/migrations/mysql.py
jetshift_core/commands/quicker.py
jetshift_core/commands/seeders/__init__.py
jetshift_core/commands/seeders/clickhouse.py
jetshift_core/commands/seeders/common.py
jetshift_core/commands/seeders/csv.py
jetshift_core/commands/seeders/mysql.py
jetshift_core/commands/seeders/seeder.py
jetshift_core/commands/version.py
jetshift_core/helpers/__init__.py
jetshift_core/helpers/clcikhouse.py
jetshift_core/helpers/common.py
jetshift_core/helpers/dev.py
jetshift_core/helpers/listeners.py
jetshift_core/helpers/mysql.py
jetshift_core/helpers/quicker.py
jetshift_core/stubs/jobs/common.yml
jetshift_core/stubs/jobs/mysql_clickhouse_insert.py
jetshift_core/stubs/jobs/simple.py
jetshift_core/stubs/migrations/sample.yml
jetshift_core/stubs/quickers/sample.yml
jetshift_core/tasks/__init__.py
jetshift_core/tasks/mysql_clickhouse_insert.py
jetshift_core/tasks/mysql_clickhouse_insert_or_update.py
jetshift_core/utils/__init__.py
jetshift_core/utils/database/__init__.py
jetshift_core/utils/database/sqlalchemy_clickhouse.py
jetshift_core/utils/database/sqlalchemy_mysql.py
jetshift_core-1.0.0a31.dist-info/LICENSE
jetshift_core-1.0.0a31.dist-info/METADATA
jetshift_core-1.0.0a31.dist-info/WHEEL
jetshift_core-1.0.0a31.dist-info/RECORD
