Metadata-Version: 2.1
Name: jetshift-core
Version: 1.0.0a31
Summary: JetShift is a powerful and lightweight ETL framework that simplifies the process of building data pipelines.
Home-page: https://jetshift.vercel.app
Author: Md Obydullah
Author-email: hi@obydul.me
Requires-Python: >=3.9,<4.0
Classifier: Programming Language :: Python :: 3
Classifier: Programming Language :: Python :: 3.9
Classifier: Programming Language :: Python :: 3.10
Classifier: Programming Language :: Python :: 3.11
Classifier: Programming Language :: Python :: 3.12
Requires-Dist: click (>=8.1.7,<9.0.0)
Requires-Dist: clickhouse-driver (==0.2.9)
Requires-Dist: clickhouse-sqlalchemy (==0.3.2)
Requires-Dist: faker (==27.4.0)
Requires-Dist: luigi (==3.5.1)
Requires-Dist: pandas (==2.2.2)
Requires-Dist: pymysql (==1.1.1)
Requires-Dist: pyyaml (>=6.0.2,<7.0.0)
Requires-Dist: requests (==2.32.3)
Requires-Dist: sqlalchemy (==2.0.34)
Project-URL: Repository, https://github.com/jetshift/core.git
